AUTHORS
CHANGELOG
MANIFEST.in
README.rst
setup.py
django_rules_light.egg-info/PKG-INFO
django_rules_light.egg-info/SOURCES.txt
django_rules_light.egg-info/dependency_links.txt
django_rules_light.egg-info/not-zip-safe
django_rules_light.egg-info/requires.txt
django_rules_light.egg-info/top_level.txt
rules_light/__init__.py
rules_light/class_decorator.py
rules_light/decorators.py
rules_light/exceptions.py
rules_light/middleware.py
rules_light/models.py
rules_light/registry.py
rules_light/rules_light_registry.py
rules_light/shortcuts.py
rules_light/urls.py
rules_light/views.py
rules_light/locale/el/LC_MESSAGES/django.mo
rules_light/locale/el/LC_MESSAGES/django.po
rules_light/locale/fr/LC_MESSAGES/django.mo
rules_light/locale/fr/LC_MESSAGES/django.po
rules_light/locale/pt_BR/LC_MESSAGES/django.mo
rules_light/locale/pt_BR/LC_MESSAGES/django.po
rules_light/static/rules_light/github.css
rules_light/static/rules_light/rainbow-custom.min.js
rules_light/templates/rules_light/base.html
rules_light/templates/rules_light/exception.html
rules_light/templates/rules_light/registry.html
rules_light/templatetags/__init__.py
rules_light/templatetags/rules_light_tags.py
rules_light/tests/__init__.py
rules_light/tests/autodiscover.py
rules_light/tests/class_decorator.py
rules_light/tests/class_decorator_classes.py
rules_light/tests/decorators.py
rules_light/tests/middleware.py
rules_light/tests/registry.py
rules_light/tests/shortcuts.py
rules_light/tests/views.py