Metadata-Version: 1.1
Name: django-rules-light
Version: 0.1.3
Summary: Rule registry for django
Home-page: http://github.com/yourlabs/django-rules-light
Author: James Pic
Author-email: jamespic@gmail.com
License: MIT
Keywords: django security rules acl rbac
Platform: UNKNOWN
Classifier: Development Status :: 5 - Production/Stable
Classifier: Intended Audience :: Developers
Classifier: License :: OSI Approved :: MIT License
Classifier: Operating System :: OS Independent
Classifier: Programming Language :: Python
Classifier: Programming Language :: Python :: 2
Classifier: Programming Language :: Python :: 3
Classifier: Topic :: Software Development :: Libraries :: Python Modules
